jirajumper/__init__.py
jirajumper/cache/__init__.py
jirajumper/cache/actions.py
jirajumper/cache/cache.py
jirajumper/cache/models.py
jirajumper/cli.py
jirajumper/client.py
jirajumper/commands/__init__.py
jirajumper/commands/clone.py
jirajumper/commands/comment.py
jirajumper/commands/fork.py
jirajumper/commands/graph.py
jirajumper/commands/link.py
jirajumper/commands/list_issues.py
jirajumper/commands/select.py
jirajumper/commands/status.py
jirajumper/commands/update.py
jirajumper/default_options.py
jirajumper/errors.py
jirajumper/fields/__init__.py
jirajumper/fields/defaults.py
jirajumper/fields/field.py
jirajumper/fields/repository.py
jirajumper/models.py
jirajumper/py.typed
jirajumper-0.1.8.dist-info/entry_points.txt
jirajumper-0.1.8.dist-info/LICENSE
jirajumper-0.1.8.dist-info/WHEEL
jirajumper-0.1.8.dist-info/METADATA
jirajumper-0.1.8.dist-info/RECORD
